gitflic/GitflicOAuthServer.py
gitflic/__init__.py
gitflic/__version__.py
gitflic/api.py
gitflic/auth.py
gitflic/exceptions.py
gitflic-1.1.dist-info/LICENSE
gitflic-1.1.dist-info/METADATA
gitflic-1.1.dist-info/WHEEL
gitflic-1.1.dist-info/top_level.txt
gitflic-1.1.dist-info/RECORD
