Metadata-Version: 2.1
Name: gitflic
Version: 1.1
Summary: GitflicApi wrapper
Home-page: https://github.com/SantaSpeen/gitflic
Author: SantaSpeen
Author-email: SantaSpeen@yandex.ru
License: MIT
Project-URL: Source, https://github.com/SantaSpeen/gitflic
Platform: UNKNOWN
Classifier: Programming Language :: Python :: 3
Classifier: License :: OSI Approved :: MIT License
Classifier: Operating System :: OS Independent
Requires-Python: >=3.7
License-File: LICENSE
Requires-Dist: requests
